go2rpm/__init__.py
go2rpm/__main__.py
go2rpm/templates/profile1.spec
go2rpm/templates/profile2.spec
go2rpm/templates/vendor.spec
go2rpm-1.18.0.dist-info/entry_points.txt
go2rpm-1.18.0.dist-info/licenses/LICENSE
go2rpm-1.18.0.dist-info/WHEEL
go2rpm-1.18.0.dist-info/METADATA
go2rpm-1.18.0.dist-info/RECORD
