Metadata-Version: 2.4
Name: go2rpm
Version: 1.18.0
Summary: Convert Go packages to RPM
Keywords: go,golang,rpm
Author-email: Robert-André Mauchin <zebob.m@gmail.com>
Requires-Python: >=3.9
Classifier: Development Status :: 5 - Production/Stable
Classifier: Intended Audience :: Developers
Classifier: License :: OSI Approved :: MIT License
Classifier: Operating System :: POSIX :: Linux
Classifier: Programming Language :: Python :: 3 :: Only
Classifier: Programming Language :: Python :: 3
Classifier: Programming Language :: Python :: 3.9
Classifier: Programming Language :: Python :: 3.10
Classifier: Programming Language :: Python :: 3.11
Classifier: Programming Language :: Python :: 3.12
Classifier: Programming Language :: Python :: 3.13
Classifier: Programming Language :: Python :: 3.14
Classifier: Topic :: Software Development :: Build Tools
Classifier: Topic :: System :: Software Distribution
Classifier: Topic :: Utilities
License-File: LICENSE
Requires-Dist: aiohttp
Requires-Dist: gitpython
Requires-Dist: jinja2
Requires-Dist: go2rpm[vendor] ; extra == "all"
Requires-Dist: pymarkdownlnt ; extra == "codeqa"
Requires-Dist: ruff>=0.3.0 ; extra == "codeqa"
Requires-Dist: go2rpm[codeqa] ; extra == "dev"
Requires-Dist: go2rpm[formatters] ; extra == "dev"
Requires-Dist: go2rpm[test] ; extra == "dev"
Requires-Dist: go2rpm[typing] ; extra == "dev"
Requires-Dist: nox ; extra == "dev"
Requires-Dist: black ; extra == "formatters"
Requires-Dist: isort ; extra == "formatters"
Requires-Dist: pytest ; extra == "test"
Requires-Dist: mypy ; extra == "typing"
Requires-Dist: pytest ; extra == "typing"
Requires-Dist: typing_extensions ; extra == "typing"
Requires-Dist: nox ; extra == "typing"
Requires-Dist: go-vendor-tools >= 0.8.0 ; extra == "vendor"
Requires-Dist: tomlkit ; extra == "vendor"
Project-URL: Homepage, https://gitlab.com/fedora/sigs/go/go2rpm
Provides-Extra: all
Provides-Extra: codeqa
Provides-Extra: dev
Provides-Extra: formatters
Provides-Extra: test
Provides-Extra: typing
Provides-Extra: vendor
